betterboto/__init__.py
betterboto/budgets.py
betterboto/client.py
betterboto/cloudformation.py
betterboto/codebuild.py
betterboto/codecommit.py
betterboto/guardduty.py
betterboto/organizations.py
betterboto/servicecatalog.py
betterboto/ssm.py
betterboto/utils.py
better_boto-0.43.0.dist-info/LICENSE
better_boto-0.43.0.dist-info/METADATA
better_boto-0.43.0.dist-info/WHEEL
better_boto-0.43.0.dist-info/top_level.txt
better_boto-0.43.0.dist-info/RECORD
