Metadata-Version: 2.1
Name: better-boto
Version: 0.43.0
Summary: Helpers to make using boto3 more enjoyable
Home-page: https://github.com/eamonnfaherty/better-boto
Author: Eamonn Faherty
Author-email: python-packages@designandsolve.co.uk
License: UNKNOWN
Platform: UNKNOWN
Classifier: Programming Language :: Python :: 3
Classifier: License :: OSI Approved :: MIT License
Classifier: Operating System :: OS Independent
License-File: LICENSE
Requires-Dist: boto3
Requires-Dist: pyyaml (>=4.2b1)
